Metadata-Version: 2.1
Name: odoo13-addon-product-brand
Version: 13.0.2.0.2
Summary: Product Brand Manager
Home-page: https://github.com/OCA/brand
Author: NetAndCo, Akretion, Prisnet Telecommunications SA, MONK Software, SerpentCS Pvt. Ltd., Tecnativa, Kaushal Prajapati, Odoo Community Association (OCA)
Author-email: support@odoo-community.org
License: AGPL-3
Platform: UNKNOWN
Classifier: Programming Language :: Python
Classifier: Framework :: Odoo
Classifier: License :: OSI Approved :: GNU Affero General Public License v3
Classifier: Development Status :: 6 - Mature
Requires-Python: >=3.5
Requires-Dist: odoo (<13.1dev,>=13.0a)
